geopre/__init__.py
geopre/cloud_masking.py
geopre/scaling_reproject_mask.py
geopre/stacking.py
geopre/water_masking.py
geopre-0.3.0.dist-info/licenses/LICENSE
geopre-0.3.0.dist-info/METADATA
geopre-0.3.0.dist-info/WHEEL
geopre-0.3.0.dist-info/top_level.txt
geopre-0.3.0.dist-info/RECORD
