Metadata-Version: 2.4
Name: geopre
Version: 0.3.0
Summary: Preprocessing tools for satellite imagery analysis
Home-page: https://github.com/MatteoGF/GeoPre
Author: Matteo Gobbi Frattini, Liang Zhongyou
Author-email: matteo.gf@live.it
License: MIT
Keywords: geospatial preprocessing remote sensing satellite imagery
Classifier: Development Status :: 4 - Beta
Classifier: Intended Audience :: Developers
Classifier: Intended Audience :: Science/Research
Classifier: Topic :: Scientific/Engineering :: GIS
Classifier: Operating System :: OS Independent
Classifier: License :: OSI Approved :: MIT License
Classifier: Programming Language :: Python :: 3
Classifier: Programming Language :: Python :: 3.7
Classifier: Programming Language :: Python :: 3.8
Classifier: Programming Language :: Python :: 3.9
Classifier: Programming Language :: Python :: 3.10
Classifier: Programming Language :: Python :: 3.11
Requires-Python: >=3.7, <3.12
License-File: LICENSE
Requires-Dist: omnicloudmask
Requires-Dist: numpy
Requires-Dist: rasterio
Requires-Dist: geopandas
Requires-Dist: pyproj
Requires-Dist: rioxarray
Requires-Dist: xarray
Requires-Dist: shapely
Requires-Dist: pathlib
Requires-Dist: typing
Dynamic: author
Dynamic: author-email
Dynamic: classifier
Dynamic: description
Dynamic: description-content-type
Dynamic: home-page
Dynamic: keywords
Dynamic: license
Dynamic: license-file
Dynamic: requires-dist
Dynamic: requires-python
Dynamic: summary
